askagent/__init__.py
askagent/askagent.py
askagent/llm_tools.py
askagent-0.1.1.dist-info/LICENSE
askagent-0.1.1.dist-info/METADATA
askagent-0.1.1.dist-info/WHEEL
askagent-0.1.1.dist-info/entry_points.txt
askagent-0.1.1.dist-info/RECORD
