Metadata-Version: 2.1
Name: askagent
Version: 0.1.1
Summary: LLM-based agents to be run from terminal to perform differen tasks with the command askagent
Home-page: https://github.com/touhi99/askagent
License: MIT
Author: Touhidul Alam
Requires-Python: >=3.10,<4.0
Classifier: License :: OSI Approved :: MIT License
Classifier: Programming Language :: Python :: 3
Classifier: Programming Language :: Python :: 3.10
Classifier: Programming Language :: Python :: 3.11
Classifier: Programming Language :: Python :: 3.12
Requires-Dist: arxiv (>=2.1.0,<3.0.0)
Requires-Dist: google-search-results (>=2.4.2,<3.0.0)
Requires-Dist: langchain (>=0.1.16,<0.2.0)
Requires-Dist: langchain-community (>=0.0.34,<0.0.35)
Requires-Dist: langchain-core (>=0.1.45,<0.2.0)
Requires-Dist: langchain-experimental (>=0.0.57,<0.0.58)
Requires-Dist: langchain-groq (>=0.1.2,<0.2.0)
Requires-Dist: langchain-openai (>=0.1.3,<0.2.0)
Requires-Dist: numexpr (>=2.10.0,<3.0.0)
Requires-Dist: python-dotenv (>=1.0.1,<2.0.0)
Requires-Dist: tavily-python (>=0.3.3,<0.4.0)
Requires-Dist: wikipedia (>=1.4.0,<2.0.0)
Requires-Dist: wolframalpha (>=5.0.0,<6.0.0)
Requires-Dist: xmltodict (>=0.13.0,<0.14.0)
Project-URL: Repository, https://github.com/touhi99/askagent
